wilson_beta/__init__.py
wilson_beta/beta_patch.py
wilson_beta-1.0.5.dist-info/licenses/LICENSE
wilson_beta-1.0.5.dist-info/METADATA
wilson_beta-1.0.5.dist-info/WHEEL
wilson_beta-1.0.5.dist-info/top_level.txt
wilson_beta-1.0.5.dist-info/RECORD
